ontolearn/__init__.py
ontolearn/abstracts.py
ontolearn/base_concept_learner.py
ontolearn/base_nces.py
ontolearn/binders.py
ontolearn/clip_architectures.py
ontolearn/clip_trainer.py
ontolearn/concept_generator.py
ontolearn/concept_learner.py
ontolearn/data_struct.py
ontolearn/ea_algorithms.py
ontolearn/ea_initialization.py
ontolearn/ea_utils.py
ontolearn/executor.py
ontolearn/experiments.py
ontolearn/fitness_functions.py
ontolearn/heuristics.py
ontolearn/incomplete_kb.py
ontolearn/knowledge_base.py
ontolearn/learning_problem.py
ontolearn/learning_problem_generator.py
ontolearn/metrics.py
ontolearn/nces_architectures.py
ontolearn/nces_modules.py
ontolearn/nces_trainer.py
ontolearn/nces_utils.py
ontolearn/owl_neural_reasoner.py
ontolearn/quality_funcs.py
ontolearn/refinement_operators.py
ontolearn/search.py
ontolearn/semantic_caching.py
ontolearn/tentris.py
ontolearn/triple_store.py
ontolearn/value_splitter.py
ontolearn/verbalizer.py
ontolearn/learners/__init__.py
ontolearn/learners/celoe.py
ontolearn/learners/drill.py
ontolearn/learners/nero.py
ontolearn/learners/ocel.py
ontolearn/learners/sparql_query_learner.py
ontolearn/learners/tree_learner.py
ontolearn/lp_generator/__init__.py
ontolearn/lp_generator/generate_data.py
ontolearn/lp_generator/helper_classes.py
ontolearn/scripts/__init__.py
ontolearn/scripts/litserve_neural_reasoner.py
ontolearn/scripts/run.py
ontolearn/utils/__init__.py
ontolearn/utils/log_config.py
ontolearn/utils/oplogging.py
ontolearn/utils/static_funcs.py
tests/__init__.py
tests/test_base_concept_learner.py
tests/test_celoe.py
tests/test_clip.py
tests/test_clip_trainer.py
tests/test_concept.py
tests/test_core_owl_hierarchy.py
tests/test_core_utils_length.py
tests/test_drill.py
tests/test_evolearner.py
tests/test_example_celoe.py
tests/test_example_concept_learning_evaluation.py
tests/test_example_concept_learning_neural_evaluation.py
tests/test_integration_with_sync_reasoner.py
tests/test_knowledge_base.py
tests/test_learners_regression.py
ontolearn-0.9.2.dist-info/LICENSE
ontolearn-0.9.2.dist-info/METADATA
ontolearn-0.9.2.dist-info/WHEEL
ontolearn-0.9.2.dist-info/entry_points.txt
ontolearn-0.9.2.dist-info/top_level.txt
ontolearn-0.9.2.dist-info/RECORD
