Metadata-Version: 2.1
Name: ontolearn
Version: 0.9.2
Summary: Ontolearn is an open-source software library for structured machine learning in Python. Ontolearn includes modules for processing knowledge bases, inductive logic programming and ontology engineering.
Home-page: https://github.com/dice-group/Ontolearn
Author: Caglar Demir
Author-email: caglardemir8@gmail.com
Classifier: Programming Language :: Python :: 3.10
Classifier: License :: OSI Approved :: MIT License
Classifier: Topic :: Scientific/Engineering :: Artificial Intelligence
Requires-Python: >=3.10.13
License-File: LICENSE
Requires-Dist: matplotlib >=3.3.4
Requires-Dist: torch ==2.2.0
Requires-Dist: rdflib >=6.0.2
Requires-Dist: pandas >=1.5.0
Requires-Dist: sortedcontainers >=2.4.0
Requires-Dist: owlapy ==1.5.1
Requires-Dist: flask >=1.1.2
Requires-Dist: tqdm >=4.64.0
Requires-Dist: transformers >=4.38.1
Requires-Dist: dicee ==0.1.4
Requires-Dist: deap >=1.3.1
Requires-Dist: fastapi >=0.110.1
Requires-Dist: uvicorn >=0.29.0
Requires-Dist: openai >=1.86.0
Provides-Extra: doc
Requires-Dist: sphinx >=7.2.6 ; extra == 'doc'
Requires-Dist: sphinx-autoapi >=3.0.0 ; extra == 'doc'
Requires-Dist: sphinx-theme >=1.0 ; extra == 'doc'
Requires-Dist: sphinx-rtd-theme >=2.0.0 ; extra == 'doc'
Requires-Dist: sphinxcontrib-plantuml >=0.27 ; extra == 'doc'
Requires-Dist: plantuml-local-client >=1.2022.6 ; extra == 'doc'
Requires-Dist: myst-parser >=2.0.0 ; extra == 'doc'
Provides-Extra: full
Requires-Dist: matplotlib >=3.3.4 ; extra == 'full'
Requires-Dist: torch ==2.2.0 ; extra == 'full'
Requires-Dist: rdflib >=6.0.2 ; extra == 'full'
Requires-Dist: pandas >=1.5.0 ; extra == 'full'
Requires-Dist: sortedcontainers >=2.4.0 ; extra == 'full'
Requires-Dist: owlapy ==1.5.1 ; extra == 'full'
Requires-Dist: flask >=1.1.2 ; extra == 'full'
Requires-Dist: tqdm >=4.64.0 ; extra == 'full'
Requires-Dist: transformers >=4.38.1 ; extra == 'full'
Requires-Dist: dicee ==0.1.4 ; extra == 'full'
Requires-Dist: deap >=1.3.1 ; extra == 'full'
Requires-Dist: fastapi >=0.110.1 ; extra == 'full'
Requires-Dist: uvicorn >=0.29.0 ; extra == 'full'
Requires-Dist: openai >=1.86.0 ; extra == 'full'
Requires-Dist: httpx >=0.25.2 ; extra == 'full'
Requires-Dist: pytest >=7.2.2 ; extra == 'full'
Requires-Dist: ontosample >=0.2.2 ; extra == 'full'
Requires-Dist: ruff >=0.7.2 ; extra == 'full'
Provides-Extra: min
Requires-Dist: matplotlib >=3.3.4 ; extra == 'min'
Requires-Dist: torch ==2.2.0 ; extra == 'min'
Requires-Dist: rdflib >=6.0.2 ; extra == 'min'
Requires-Dist: pandas >=1.5.0 ; extra == 'min'
Requires-Dist: sortedcontainers >=2.4.0 ; extra == 'min'
Requires-Dist: owlapy ==1.5.1 ; extra == 'min'
Requires-Dist: flask >=1.1.2 ; extra == 'min'
Requires-Dist: tqdm >=4.64.0 ; extra == 'min'
Requires-Dist: transformers >=4.38.1 ; extra == 'min'
Requires-Dist: dicee ==0.1.4 ; extra == 'min'
Requires-Dist: deap >=1.3.1 ; extra == 'min'
Requires-Dist: fastapi >=0.110.1 ; extra == 'min'
Requires-Dist: uvicorn >=0.29.0 ; extra == 'min'
Requires-Dist: openai >=1.86.0 ; extra == 'min'
